[
    { "strName" : "RCSDistro08DmgRepair", "strActionCO" : "ItmRCSDistro08Dmg", "strActionGroup" : "Work", "strTooltip" : "Repairs item to a functional state.",  "strInteractionTemplate" : "ACTRepairTEMP", "CTThem" :  "TIsRepairableNotContained" , "aInputs" : [ "TIsMotor=1.0x1", "TIsHeatSink=1.0x1", "TIsPartsMechSmall=1.0x3", "TIsScrapAluminum=1.0x1", "TIsScrapCarbonFiber=1.0x1" ], "fTargetPointRange" : 2.0, "fDuration" : 0.001, "bSparks" : true, "aToolCTsUse" : [ "TIsToolMortorq", "TIsToolSoldering" ], "aLootCOs" : [ "ItmRCSDistro08" ], "strJobType" : "repair", "strAllowLootCTsUs" : "CTWorkProgressCTRL", "strAllowLootCTsThem" : "CONDRepairProgressx5", "strProgressStat" : "StatRepairProgress", "strCTThemMultCondTools" : "IsToolMortorq", "strCTThemMultCondUs" : "StatInstallRateCTRL" },
    { "strName" : "RCSDistro08DmgLooseRepair", "strActionCO" : "ItmRCSDistro08DmgLoose", "strActionGroup" : "Work", "strTooltip" : "Repairs item to a functional state.",  "strInteractionTemplate" : "ACTRepairTEMP", "CTThem" :  "TIsRepairableNotContained" , "aInputs" : [ "TIsMotor=1.0x1", "TIsHeatSink=1.0x1", "TIsPartsMechSmall=1.0x3", "TIsScrapAluminum=1.0x1", "TIsScrapCarbonFiber=1.0x1" ], "fTargetPointRange" : 2.0, "fDuration" : 0.001, "bSparks" : true, "aToolCTsUse" : [ "TIsToolMortorq", "TIsToolSoldering" ], "aLootCOs" : [ "ItmRCSDistro08Loose" ], "strJobType" : "repair", "strAllowLootCTsUs" : "CTWorkProgressCTRL", "strAllowLootCTsThem" : "CONDRepairProgressx5", "strProgressStat" : "StatRepairProgress", "strCTThemMultCondTools" : "IsToolMortorq", "strCTThemMultCondUs" : "StatInstallRateCTRL" }
]